[{"contact":"-","description":"-","facebook":"-","hours":"-","id":4728,"location":"2038-2039-2040","mall_id":17,"map_id":null,"store_id":1873,"twitter":"-","website":"-","x":0,"y":0,"store_name":"Dave's Funhouse","mall_name":"Centrio","logo_url":null,"photo_url":null,"categories":[{"id":1,"name":"Amusement and Entertainment"}]},{"contact":"-","description":"-","facebook":"-","hours":"-","id":4731,"location":"3005-3006","mall_id":17,"map_id":null,"store_id":959,"twitter":"-","website":"-","x":0,"y":0,"store_name":"Little Martians","mall_name":"Centrio","logo_url":null,"photo_url":null,"categories":[{"id":1,"name":"Amusement and Entertainment"},{"id":5,"name":"Children's Shops"}]},{"contact":"-","description":"-","facebook":"-","hours":"-","id":4732,"location":"3001","mall_id":17,"map_id":null,"store_id":1664,"twitter":"-","website":"-","x":0,"y":0,"store_name":"Timezone","mall_name":"Centrio","logo_url":null,"photo_url":null,"categories":[{"id":1,"name":"Amusement and Entertainment"}]},{"contact":"-","description":"--","facebook":"-","hours":"-","id":4734,"location":"2069","mall_id":17,"map_id":null,"store_id":1878,"twitter":"-","website":"-","x":0,"y":0,"store_name":"Wonderland for Kids","mall_name":"Centrio","logo_url":null,"photo_url":null,"categories":[{"id":17,"name":"Services"}]},{"contact":"-","description":"-","facebook":"-","hours":"-","id":4736,"location":"2132","mall_id":17,"map_id":null,"store_id":82,"twitter":"-","website":"-","x":0,"y":0,"store_name":"Arrow","mall_name":"Centrio","logo_url":null,"photo_url":null,"categories":[{"id":2,"name":"Apparel"}]},{"contact":"-","description":"-","facebook":"-","hours":"-","id":4737,"location":"1026","mall_id":17,"map_id":null,"store_id":86,"twitter":"-","website":"-","x":0,"y":0,"store_name":"Artwork","mall_name":"Centrio","logo_url":null,"photo_url":null,"categories":[{"id":2,"name":"Apparel"}]},{"contact":"-","description":"-","facebook":"-","hours":"-","id":4742,"location":"1078-1081","mall_id":17,"map_id":null,"store_id":166,"twitter":"-","website":"-","x":0,"y":0,"store_name":"Bench","mall_name":"Centrio","logo_url":null,"photo_url":null,"categories":[{"id":2,"name":"Apparel"}]},{"contact":"-","description":"-","facebook":"-","hours":"-","id":4744,"location":"2016-2017","mall_id":17,"map_id":null,"store_id":2438,"twitter":"-","website":"-","x":0,"y":0,"store_name":"Bettina","mall_name":"Centrio","logo_url":null,"photo_url":null,"categories":[{"id":2,"name":"Apparel"}]},{"contact":"-","description":"-","facebook":"-","hours":"-","id":4745,"location":"1132-1136","mall_id":17,"map_id":null,"store_id":2439,"twitter":"-","website":"-","x":0,"y":0,"store_name":"Brandsmart","mall_name":"Centrio","logo_url":null,"photo_url":null,"categories":[{"id":2,"name":"Apparel"}]},{"contact":"-","description":"-","facebook":"--","hours":"-","id":4746,"location":"1017","mall_id":17,"map_id":null,"store_id":262,"twitter":"-","website":"-","x":0,"y":0,"store_name":"Collezione/C2","mall_name":"Centrio","logo_url":null,"photo_url":null,"categories":[{"id":2,"name":"Apparel"}]},{"contact":"-","description":"-","facebook":"-","hours":"-","id":4747,"location":"2090","mall_id":17,"map_id":null,"store_id":375,"twitter":"--","website":"-","x":0,"y":0,"store_name":"Columbia","mall_name":"Centrio","logo_url":null,"photo_url":null,"categories":[{"id":2,"name":"Apparel"},{"id":20,"name":"Sports Shops"}]},{"contact":"-","description":"-","facebook":"-","hours":"-","id":4751,"location":"1121-1123","mall_id":17,"map_id":null,"store_id":2441,"twitter":"-","website":"-","x":0,"y":0,"store_name":"DB 158","mall_name":"Centrio","logo_url":null,"photo_url":null,"categories":[{"id":2,"name":"Apparel"}]},{"contact":"-","description":"-","facebook":"-","hours":"-","id":4753,"location":"2010","mall_id":17,"map_id":null,"store_id":459,"twitter":"-","website":"-","x":0,"y":0,"store_name":"Dickies","mall_name":"Centrio","logo_url":null,"photo_url":null,"categories":[{"id":2,"name":"Apparel"}]},{"contact":"-","description":"-","facebook":"-","hours":"-","id":4754,"location":"2134","mall_id":17,"map_id":null,"store_id":475,"twitter":"-","website":"-","x":0,"y":0,"store_name":"Dockers","mall_name":"Centrio","logo_url":null,"photo_url":null,"categories":[{"id":2,"name":"Apparel"},{"id":18,"name":"Shoes, Bags, Leather Goods"}]},{"contact":"-","description":"-","facebook":"-","hours":"-","id":4755,"location":"1042","mall_id":17,"map_id":null,"store_id":496,"twitter":"-","website":"-","x":0,"y":0,"store_name":"Esprit","mall_name":"Centrio","logo_url":null,"photo_url":null,"categories":[{"id":2,"name":"Apparel"}]},{"contact":"-","description":"-","facebook":"-","hours":"-","id":4759,"location":"1091-1092","mall_id":17,"map_id":null,"store_id":2444,"twitter":"-","website":"-","x":0,"y":0,"store_name":"F & X","mall_name":"Centrio","logo_url":null,"photo_url":null,"categories":[{"id":2,"name":"Apparel"}]},{"contact":"-","description":"-","facebook":"-","hours":"-","id":4760,"location":"1018-1019","mall_id":17,"map_id":null,"store_id":574,"twitter":"-","website":"-","x":0,"y":0,"store_name":"Folded & Hung","mall_name":"Centrio","logo_url":null,"photo_url":null,"categories":[{"id":2,"name":"Apparel"}]},{"contact":"-","description":"-","facebook":"-","hours":"-","id":4761,"location":"1015-1016","mall_id":17,"map_id":null,"store_id":580,"twitter":"-","website":"-","x":0,"y":0,"store_name":"For Me","mall_name":"Centrio","logo_url":null,"photo_url":null,"categories":[{"id":2,"name":"Apparel"}]},{"contact":"-","description":"-","facebook":"-","hours":"-","id":4763,"location":"1036-1037","mall_id":17,"map_id":null,"store_id":656,"twitter":"-","website":"-","x":0,"y":0,"store_name":"Giordano","mall_name":"Centrio","logo_url":null,"photo_url":null,"categories":[{"id":2,"name":"Apparel"}]},{"contact":"-","description":"-","facebook":"-","hours":"-","id":4764,"location":"1104-1106","mall_id":17,"map_id":null,"store_id":690,"twitter":"-","website":"-","x":0,"y":0,"store_name":"Guess","mall_name":"Centrio","logo_url":null,"photo_url":null,"categories":[{"id":2,"name":"Apparel"},{"id":18,"name":"Shoes, Bags, Leather Goods"}]},{"contact":"-","description":"-","facebook":"-","hours":"-","id":4765,"location":"1029-1030","mall_id":17,"map_id":null,"store_id":762,"twitter":"-","website":"-","x":0,"y":0,"store_name":"Human","mall_name":"Centrio","logo_url":null,"photo_url":null,"categories":[{"id":2,"name":"Apparel"}]},{"contact":"-","description":"-","facebook":"-","hours":"-","id":4766,"location":"2063","mall_id":17,"map_id":null,"store_id":817,"twitter":"-","website":"-","x":0,"y":0,"store_name":"Jag","mall_name":"Centrio","logo_url":null,"photo_url":null,"categories":[{"id":2,"name":"Apparel"}]},{"contact":"-","description":"-","facebook":"-","hours":"-","id":4767,"location":"1020-1021","mall_id":17,"map_id":null,"store_id":860,"twitter":"-","website":"-","x":0,"y":0,"store_name":"Kamiseta","mall_name":"Centrio","logo_url":null,"photo_url":null,"categories":[{"id":2,"name":"Apparel"}]},{"contact":"-","description":"-","facebook":"-","hours":"-","id":4769,"location":"1028","mall_id":17,"map_id":null,"store_id":865,"twitter":"-","website":"-","x":0,"y":0,"store_name":"Kashieca","mall_name":"Centrio","logo_url":null,"photo_url":null,"categories":[{"id":2,"name":"Apparel"}]},{"contact":"-","description":"-","facebook":"-","hours":"-","id":4770,"location":"2063","mall_id":17,"map_id":null,"store_id":947,"twitter":"-","website":"-","x":0,"y":0,"store_name":"Levi's","mall_name":"Centrio","logo_url":null,"photo_url":null,"categories":[{"id":2,"name":"Apparel"}]},{"contact":"-","description":"-","facebook":"-","hours":"-","id":4771,"location":"1011","mall_id":17,"map_id":null,"store_id":964,"twitter":"-","website":"-","x":0,"y":0,"store_name":"Loalde","mall_name":"Centrio","logo_url":null,"photo_url":null,"categories":[{"id":2,"name":"Apparel"}]},{"contact":"-","description":"-","facebook":"-","hours":"-","id":4772,"location":"1102-1103","mall_id":17,"map_id":null,"store_id":1010,"twitter":"-","website":"-","x":0,"y":0,"store_name":"Mango","mall_name":"Centrio","logo_url":null,"photo_url":null,"categories":[{"id":2,"name":"Apparel"}]},{"contact":"--","description":"-","facebook":"-","hours":"-","id":4773,"location":"2136","mall_id":17,"map_id":null,"store_id":1071,"twitter":"-","website":"-","x":0,"y":0,"store_name":"Mint","mall_name":"Centrio","logo_url":null,"photo_url":null,"categories":[{"id":2,"name":"Apparel"}]},{"contact":"-","description":"-","facebook":"-","hours":"-","id":4774,"location":"2025-2026","mall_id":17,"map_id":null,"store_id":1094,"twitter":"-","website":"-","x":0,"y":0,"store_name":"Mossimo","mall_name":"Centrio","logo_url":null,"photo_url":null,"categories":[{"id":2,"name":"Apparel"}]},{"contact":"-","description":"-","facebook":"-","hours":"-","id":4775,"location":"1084","mall_id":17,"map_id":null,"store_id":1133,"twitter":"-","website":"-","x":0,"y":0,"store_name":"Nautica","mall_name":"Centrio","logo_url":null,"photo_url":null,"categories":[{"id":2,"name":"Apparel"}]},{"contact":"-","description":"-","facebook":"-","hours":"-","id":4776,"location":"1012-1014","mall_id":17,"map_id":null,"store_id":1205,"twitter":"-","website":"-","x":0,"y":0,"store_name":"Oxygen","mall_name":"Centrio","logo_url":null,"photo_url":null,"categories":[{"id":2,"name":"Apparel"}]},{"contact":"-","description":"-","facebook":"-","hours":"-","id":4778,"location":"1096A-1097A","mall_id":17,"map_id":null,"store_id":1241,"twitter":"-","website":"-","x":0,"y":0,"store_name":"Penshoppe","mall_name":"Centrio","logo_url":null,"photo_url":null,"categories":[{"id":2,"name":"Apparel"}]},{"contact":"-","description":"-","facebook":"-","hours":"-","id":4779,"location":"1077","mall_id":17,"map_id":null,"store_id":1242,"twitter":"-","website":"-","x":0,"y":0,"store_name":"People are People","mall_name":"Centrio","logo_url":null,"photo_url":null,"categories":[{"id":2,"name":"Apparel"}]},{"contact":"-","description":"-","facebook":"-","hours":"-","id":4780,"location":"1098A","mall_id":17,"map_id":null,"store_id":1319,"twitter":"-","website":"-","x":0,"y":0,"store_name":"Promod","mall_name":"Centrio","logo_url":null,"photo_url":null,"categories":[{"id":2,"name":"Apparel"}]},{"contact":"-","description":"-","facebook":"-","hours":"-","id":4781,"location":"1073-1076","mall_id":17,"map_id":null,"store_id":2446,"twitter":"-","website":"-","x":0,"y":0,"store_name":"Quicksilver / Roxy","mall_name":"Centrio","logo_url":null,"photo_url":null,"categories":[{"id":2,"name":"Apparel"}]},{"contact":"-","description":"-","facebook":"-","hours":"-","id":4782,"location":"2103-2104, 2063","mall_id":17,"map_id":null,"store_id":1386,"twitter":"-","website":"-","x":0,"y":0,"store_name":"R.O.X.","mall_name":"Centrio","logo_url":null,"photo_url":null,"categories":[{"id":20,"name":"Sports Shops"}]},{"contact":"-","description":"-","facebook":"-","hours":"-","id":4787,"location":"2011","mall_id":17,"map_id":null,"store_id":2450,"twitter":"-","website":"-","x":0,"y":0,"store_name":"RRJ","mall_name":"Centrio","logo_url":null,"photo_url":null,"categories":[{"id":2,"name":"Apparel"}]},{"contact":"-","description":"-","facebook":"-","hours":"-","id":4788,"location":"2049-2050","mall_id":17,"map_id":null,"store_id":1784,"twitter":"-","website":"-","x":0,"y":0,"store_name":"What A Girl Wants","mall_name":"Centrio","logo_url":null,"photo_url":null,"categories":[{"id":2,"name":"Apparel"}]},{"contact":"-","description":"-","facebook":"-","hours":"-","id":4789,"location":"2044-2045","mall_id":17,"map_id":null,"store_id":1793,"twitter":"-","website":"-","x":0,"y":0,"store_name":"Wrangler","mall_name":"Centrio","logo_url":null,"photo_url":null,"categories":[{"id":2,"name":"Apparel"}]},{"contact":"-","description":"-","facebook":"-","hours":"-","id":4791,"location":"1068-1069","mall_id":17,"map_id":null,"store_id":228,"twitter":"-","website":"-","x":0,"y":0,"store_name":"BPI Bank","mall_name":"Centrio","logo_url":null,"photo_url":null,"categories":[{"id":3,"name":"Banks/ATM's"}]},{"contact":"-","description":"-","facebook":"-","hours":"-","id":4792,"location":"2067","mall_id":17,"map_id":null,"store_id":2306,"twitter":"-","website":"-","x":0,"y":0,"store_name":"BPI ATM Center","mall_name":"Centrio","logo_url":null,"photo_url":null,"categories":[{"id":3,"name":"Banks/ATM's"}]},{"contact":"-","description":"-","facebook":"-","hours":"-","id":4793,"location":"1001","mall_id":17,"map_id":null,"store_id":1127,"twitter":"-","website":"-","x":0,"y":0,"store_name":"National Bookstore","mall_name":"Centrio","logo_url":null,"photo_url":null,"categories":[{"id":4,"name":"Bookstores/Office Supplies/Stationeries"}]},{"contact":"-","description":"-","facebook":"-","hours":"-","id":4794,"location":"2057","mall_id":17,"map_id":null,"store_id":336,"twitter":"-","website":"-","x":0,"y":0,"store_name":"Chicco","mall_name":"Centrio","logo_url":null,"photo_url":null,"categories":[{"id":2,"name":"Apparel"}]},{"contact":"-","description":"-","facebook":"-","hours":"-","id":4795,"location":"2036","mall_id":17,"map_id":null,"store_id":2451,"twitter":"--","website":"-","x":0,"y":0,"store_name":"Children's World","mall_name":"Centrio","logo_url":null,"photo_url":null,"categories":[{"id":5,"name":"Children's Shops"}]},{"contact":"-","description":"-","facebook":"-","hours":"-","id":4796,"location":"2023-2024","mall_id":17,"map_id":null,"store_id":654,"twitter":"-","website":"-","x":0,"y":0,"store_name":"Gingersnaps","mall_name":"Centrio","logo_url":null,"photo_url":null,"categories":[{"id":2,"name":"Apparel"},{"id":5,"name":"Children's Shops"}]},{"contact":"-","description":"-","facebook":"-","hours":"-","id":4797,"location":"2021","mall_id":17,"map_id":null,"store_id":1838,"twitter":"-","website":"-","x":0,"y":0,"store_name":"Just G","mall_name":"Centrio","logo_url":null,"photo_url":null,"categories":[{"id":2,"name":"Apparel"}]},{"contact":"-","description":"-","facebook":"-","hours":"-","id":4798,"location":"2022","mall_id":17,"map_id":null,"store_id":1095,"twitter":"-","website":"-","x":0,"y":0,"store_name":"Mossimo Kids","mall_name":"Centrio","logo_url":null,"photo_url":null,"categories":[{"id":2,"name":"Apparel"},{"id":5,"name":"Children's Shops"}]},{"contact":"-","description":"-","facebook":"-","hours":"-","id":4799,"location":"2031-2034","mall_id":17,"map_id":null,"store_id":1098,"twitter":"-","website":"-","x":0,"y":0,"store_name":"Mothercare","mall_name":"Centrio","logo_url":null,"photo_url":null,"categories":[{"id":2,"name":"Apparel"},{"id":5,"name":"Children's Shops"}]},{"contact":"-","description":"-","facebook":"-","hours":"-","id":4800,"location":"2030","mall_id":17,"map_id":null,"store_id":1198,"twitter":"-","website":"-","x":0,"y":0,"store_name":"Osh Kosh","mall_name":"Centrio","logo_url":null,"photo_url":null,"categories":[{"id":2,"name":"Apparel"},{"id":5,"name":"Children's Shops"}]},{"contact":"-","description":"-","facebook":"-","hours":"-","id":4801,"location":"3103","mall_id":17,"map_id":null,"store_id":1895,"twitter":"-","website":"-","x":0,"y":0,"store_name":"8Telcom","mall_name":"Centrio","logo_url":null,"photo_url":null,"categories":[{"id":22,"name":"Computers/Electronics/Communication"}]},{"contact":"-","description":"-","facebook":"-","hours":"-","id":4802,"location":"3115","mall_id":17,"map_id":null,"store_id":1900,"twitter":"-","website":"-","x":0,"y":0,"store_name":"Acer","mall_name":"Centrio","logo_url":null,"photo_url":null,"categories":[{"id":22,"name":"Computers/Electronics/Communication"}]},{"contact":"-","description":"-","facebook":"-","hours":"-","id":4803,"location":"3115","mall_id":17,"map_id":null,"store_id":1900,"twitter":"-","website":"-","x":0,"y":0,"store_name":"Acer","mall_name":"Centrio","logo_url":null,"photo_url":null,"categories":[{"id":22,"name":"Computers/Electronics/Communication"}]},{"contact":"-","description":"-","facebook":"-","hours":"-","id":4804,"location":"3115","mall_id":17,"map_id":null,"store_id":1900,"twitter":"-","website":"-","x":0,"y":0,"store_name":"Acer","mall_name":"Centrio","logo_url":null,"photo_url":null,"categories":[{"id":22,"name":"Computers/Electronics/Communication"}]},{"contact":"-","description":"-","facebook":"-","hours":"-","id":4806,"location":"3088-3089","mall_id":17,"map_id":null,"store_id":2349,"twitter":"-","website":"-","x":0,"y":0,"store_name":"CD-R King","mall_name":"Centrio","logo_url":null,"photo_url":null,"categories":[{"id":22,"name":"Computers/Electronics/Communication"}]},{"contact":"-","description":"-","facebook":"-","hours":"-","id":4807,"location":"3124","mall_id":17,"map_id":null,"store_id":1905,"twitter":"-","website":"-","x":0,"y":0,"store_name":"Cherry Mobile","mall_name":"Centrio","logo_url":null,"photo_url":null,"categories":[{"id":22,"name":"Computers/Electronics/Communication"}]},{"contact":"-","description":"-","facebook":"-","hours":"-","id":4808,"location":"3112","mall_id":17,"map_id":null,"store_id":2172,"twitter":"-","website":"-","x":0,"y":0,"store_name":" Data Blitz","mall_name":"Centrio","logo_url":null,"photo_url":null,"categories":[{"id":22,"name":"Computers/Electronics/Communication"}]},{"contact":"-","description":"0","facebook":"-","hours":"-","id":4809,"location":"2087-2088","mall_id":17,"map_id":null,"store_id":467,"twitter":"-","website":"-","x":0,"y":0,"store_name":"Digital Walker","mall_name":"Centrio","logo_url":null,"photo_url":null,"categories":[{"id":22,"name":"Computers/Electronics/Communication"}]},{"contact":"-","description":"-","facebook":"-","hours":"-","id":4810,"location":"3105","mall_id":17,"map_id":null,"store_id":620,"twitter":"-","website":"-","x":0,"y":0,"store_name":"Gadgets Plus","mall_name":"Centrio","logo_url":null,"photo_url":null,"categories":[{"id":22,"name":"Computers/Electronics/Communication"}]},{"contact":"-","description":"-","facebook":"-","hours":"-","id":4811,"location":"3111","mall_id":17,"map_id":null,"store_id":1910,"twitter":"-","website":"-","x":0,"y":0,"store_name":"Gui","mall_name":"Centrio","logo_url":null,"photo_url":null,"categories":[{"id":22,"name":"Computers/Electronics/Communication"}]},{"contact":"-","description":"-","facebook":"-","hours":"-","id":4814,"location":"3090","mall_id":17,"map_id":null,"store_id":2453,"twitter":"-","website":"-","x":0,"y":0,"store_name":"HP","mall_name":"Centrio","logo_url":null,"photo_url":null,"categories":[{"id":22,"name":"Computers/Electronics/Communication"}]},{"contact":"-","description":"-","facebook":"-","hours":"-","id":4817,"location":"2085-2086","mall_id":17,"map_id":null,"store_id":769,"twitter":"-","website":"-","x":0,"y":0,"store_name":"I Store ","mall_name":"Centrio","logo_url":null,"photo_url":null,"categories":[]},{"contact":"-","description":"-","facebook":"-","hours":"-","id":4820,"location":"3101","mall_id":17,"map_id":null,"store_id":1045,"twitter":"-","website":"-","x":0,"y":0,"store_name":"Memoxpress","mall_name":"Centrio","logo_url":null,"photo_url":null,"categories":[{"id":22,"name":"Computers/Electronics/Communication"}]},{"contact":"-","description":"-","facebook":"-","hours":"-","id":4821,"location":"3098-3099","mall_id":17,"map_id":null,"store_id":1919,"twitter":"-","website":"-","x":0,"y":0,"store_name":"Octagon","mall_name":"Centrio","logo_url":null,"photo_url":null,"categories":[{"id":22,"name":"Computers/Electronics/Communication"}]},{"contact":"-","description":"-","facebook":"-","hours":"-","id":4822,"location":"3123","mall_id":17,"map_id":null,"store_id":1155,"twitter":"-","website":"-","x":0,"y":0,"store_name":"Nokia Store","mall_name":"Centrio","logo_url":null,"photo_url":null,"categories":[{"id":22,"name":"Computers/Electronics/Communication"}]},{"contact":"-","description":"-","facebook":"-","hours":"-","id":4829,"location":"3116","mall_id":17,"map_id":null,"store_id":2460,"twitter":"-","website":"-","x":0,"y":0,"store_name":"Olympus","mall_name":"Centrio","logo_url":null,"photo_url":null,"categories":[{"id":22,"name":"Computers/Electronics/Communication"}]},{"contact":"-","description":"-","facebook":"-","hours":"-","id":4834,"location":"3097","mall_id":17,"map_id":null,"store_id":2461,"twitter":"-","website":"-","x":0,"y":0,"store_name":"Oro Graphics","mall_name":"Centrio","logo_url":null,"photo_url":null,"categories":[{"id":22,"name":"Computers/Electronics/Communication"}]},{"contact":"-","description":"-","facebook":"-","hours":"-","id":4847,"location":"3110","mall_id":17,"map_id":null,"store_id":2310,"twitter":"-","website":"-","x":0,"y":0,"store_name":"ROVER SECURITY SYSTEMS","mall_name":"Centrio","logo_url":null,"photo_url":null,"categories":[{"id":22,"name":"Computers/Electronics/Communication"}]},{"contact":"-","description":"-","facebook":"-","hours":"-","id":4850,"location":"3120","mall_id":17,"map_id":null,"store_id":2311,"twitter":"-","website":"-","x":0,"y":0,"store_name":"SAMSUNG CONCEPT STORE","mall_name":"Centrio","logo_url":null,"photo_url":null,"categories":[{"id":22,"name":"Computers/Electronics/Communication"}]},{"contact":"-","description":"-","facebook":"-","hours":"-","id":4851,"location":"3119","mall_id":17,"map_id":null,"store_id":1920,"twitter":"-","website":"-","x":0,"y":0,"store_name":"Samsung I.T.","mall_name":"Centrio","logo_url":null,"photo_url":null,"categories":[{"id":22,"name":"Computers/Electronics/Communication"}]},{"contact":"-","description":"-","facebook":"-","hours":"-","id":4857,"location":"3118","mall_id":17,"map_id":null,"store_id":1921,"twitter":"-","website":"-","x":0,"y":0,"store_name":"Samsung Mobile","mall_name":"Centrio","logo_url":null,"photo_url":null,"categories":[{"id":22,"name":"Computers/Electronics/Communication"}]},{"contact":"-","description":"-","facebook":"-","hours":"-","id":4861,"location":"3093-3094","mall_id":17,"map_id":null,"store_id":2471,"twitter":"-","website":"-","x":0,"y":0,"store_name":"Sony Experience Corner","mall_name":"Centrio","logo_url":null,"photo_url":null,"categories":[{"id":22,"name":"Computers/Electronics/Communication"}]},{"contact":"-","description":"-","facebook":"-","hours":"-","id":4867,"location":"3100","mall_id":17,"map_id":null,"store_id":2473,"twitter":"-","website":"-","x":0,"y":0,"store_name":"Spacecom","mall_name":"Centrio","logo_url":null,"photo_url":null,"categories":[{"id":22,"name":"Computers/Electronics/Communication"}]},{"contact":"-","description":"-","facebook":"-","hours":"-","id":4871,"location":"-","mall_id":17,"map_id":null,"store_id":1846,"twitter":"-","website":"-","x":0,"y":0,"store_name":"Robinson's","mall_name":"Centrio","logo_url":null,"photo_url":null,"categories":[{"id":6,"name":"Department Stores"}]},{"contact":"-","description":"-","facebook":"-","hours":"-","id":4873,"location":"1052-1053","mall_id":17,"map_id":null,"store_id":1050,"twitter":"-","website":"-","x":0,"y":0,"store_name":"Mercury Drug","mall_name":"Centrio","logo_url":null,"photo_url":null,"categories":[{"id":7,"name":"Drugstore"}]},{"contact":"-","description":"-","facebook":"-","hours":"-","id":4875,"location":"2068","mall_id":17,"map_id":null,"store_id":1384,"twitter":"-","website":"-","x":0,"y":0,"store_name":"Rose Pharmacy","mall_name":"Centrio","logo_url":null,"photo_url":null,"categories":[{"id":7,"name":"Drugstore"}]},{"contact":"-","description":"-","facebook":"-","hours":"-","id":4876,"location":"2052-2056","mall_id":17,"map_id":null,"store_id":1774,"twitter":"-","website":"-","x":0,"y":0,"store_name":"Watsons","mall_name":"Centrio","logo_url":null,"photo_url":null,"categories":[{"id":7,"name":"Drugstore"},{"id":9,"name":"Health,Beauty, Wellness"}]},{"contact":"-","description":"--","facebook":"-","hours":"-","id":4879,"location":"3020-3021","mall_id":17,"map_id":null,"store_id":168,"twitter":"-","website":"-","x":0,"y":0,"store_name":"Bench Fix Salon","mall_name":"Centrio","logo_url":null,"photo_url":null,"categories":[{"id":9,"name":"Health,Beauty, Wellness"},{"id":17,"name":"Services"}]},{"contact":"-","description":"-","facebook":"-","hours":"-","id":4882,"location":"3068","mall_id":17,"map_id":null,"store_id":2482,"twitter":"-","website":"-","x":0,"y":0,"store_name":"Dermcare","mall_name":"Centrio","logo_url":null,"photo_url":null,"categories":[]},{"contact":"-","description":"-","facebook":"-","hours":"-","id":4884,"location":"1040","mall_id":17,"map_id":null,"store_id":2372,"twitter":"-","website":"-","x":0,"y":0,"store_name":"Etude House","mall_name":"Centrio","logo_url":null,"photo_url":null,"categories":[{"id":9,"name":"Health,Beauty, Wellness"}]},{"contact":"-","description":"--","facebook":"-","hours":"-","id":4885,"location":"1110-1111","mall_id":17,"map_id":null,"store_id":528,"twitter":"-","website":"-","x":0,"y":0,"store_name":"Face Shop","mall_name":"Centrio","logo_url":null,"photo_url":null,"categories":[]},{"contact":"-","description":"-","facebook":"-","hours":"-","id":4889,"location":"3077-3078","mall_id":17,"map_id":null,"store_id":581,"twitter":"-","website":"-","x":0,"y":0,"store_name":"Forever Flawless","mall_name":"Centrio","logo_url":null,"photo_url":null,"categories":[{"id":17,"name":"Services"}]},{"contact":"-","description":"-","facebook":"-","hours":"-","id":4891,"location":"1114","mall_id":17,"map_id":null,"store_id":1849,"twitter":"-","website":"-","x":0,"y":0,"store_name":"Fresh Fragrance Bar","mall_name":"Centrio","logo_url":null,"photo_url":null,"categories":[{"id":9,"name":"Health,Beauty, Wellness"}]},{"contact":"-","description":"-","facebook":"-","hours":"-","id":4893,"location":"3069","mall_id":17,"map_id":null,"store_id":2486,"twitter":"-","website":"-","x":0,"y":0,"store_name":"Hairscape.ph","mall_name":"Centrio","logo_url":null,"photo_url":null,"categories":[]},{"contact":"-","description":"-","facebook":"-","hours":"-","id":4894,"location":"3058","mall_id":17,"map_id":null,"store_id":768,"twitter":"-","website":"-","x":0,"y":0,"store_name":"I Lash Extension Salon","mall_name":"Centrio","logo_url":null,"photo_url":null,"categories":[{"id":14,"name":"Offices"}]},{"contact":"-","description":"-","facebook":"-","hours":"-","id":4896,"location":"3067","mall_id":17,"map_id":null,"store_id":869,"twitter":"-","website":"--","x":0,"y":0,"store_name":"Kenko Body Care","mall_name":"Centrio","logo_url":null,"photo_url":null,"categories":[{"id":9,"name":"Health,Beauty, Wellness"}]},{"contact":"-","description":"0","facebook":"-","hours":"0","id":4899,"location":"3059","mall_id":17,"map_id":null,"store_id":936,"twitter":"-","website":"-","x":0,"y":0,"store_name":"Lay Bare Waxing Salon","mall_name":"Centrio","logo_url":null,"photo_url":null,"categories":[{"id":9,"name":"Health,Beauty, Wellness"},{"id":14,"name":"Offices"}]},{"contact":"-","description":"0","facebook":"-","hours":"-","id":4903,"location":"3066","mall_id":17,"map_id":null,"store_id":1123,"twitter":"-","website":"-","x":0,"y":0,"store_name":"Nail-a-holics","mall_name":"Centrio","logo_url":null,"photo_url":null,"categories":[{"id":9,"name":"Health,Beauty, Wellness"},{"id":17,"name":"Services"}]},{"contact":"-","description":"-","facebook":"-","hours":"-","id":4904,"location":"3072-3074/3080","mall_id":17,"map_id":null,"store_id":1413,"twitter":"-","website":"-","x":0,"y":0,"store_name":"Salon De Rose","mall_name":"Centrio","logo_url":null,"photo_url":null,"categories":[{"id":9,"name":"Health,Beauty, Wellness"},{"id":17,"name":"Services"}]},{"contact":"-","description":"-0","facebook":"-","hours":"-","id":4907,"location":"3060-3061","mall_id":17,"map_id":null,"store_id":2493,"twitter":"-","website":"-","x":0,"y":0,"store_name":"Skin R Us","mall_name":"Centrio","logo_url":null,"photo_url":null,"categories":[]},{"contact":"-","description":"0","facebook":"-","hours":"-","id":4909,"location":"3063","mall_id":17,"map_id":null,"store_id":2495,"twitter":"-","website":"-","x":0,"y":0,"store_name":"Vanityworks","mall_name":"Centrio","logo_url":null,"photo_url":null,"categories":[]},{"contact":"-","description":"0","facebook":"-","hours":"-","id":4911,"location":"1022","mall_id":17,"map_id":null,"store_id":1756,"twitter":"-","website":"-","x":0,"y":0,"store_name":"VMV Hypoallergenics","mall_name":"Centrio","logo_url":null,"photo_url":null,"categories":[{"id":9,"name":"Health,Beauty, Wellness"}]},{"contact":"-","description":"0","facebook":"-","hours":"-","id":4912,"location":"1051","mall_id":17,"map_id":null,"store_id":2361,"twitter":"-","website":"-","x":0,"y":0,"store_name":"Yves Rocher","mall_name":"Centrio","logo_url":null,"photo_url":null,"categories":[{"id":9,"name":"Health,Beauty, Wellness"}]},{"contact":"-","description":"0","facebook":"-","hours":"-","id":4914,"location":"2001","mall_id":17,"map_id":null,"store_id":13,"twitter":"-","website":"-","x":0,"y":0,"store_name":"Abenson","mall_name":"Centrio","logo_url":null,"photo_url":null,"categories":[{"id":10,"name":"Home & Appliances"}]},{"contact":"-","description":"-","facebook":"-","hours":"-","id":4916,"location":"3007-3009","mall_id":17,"map_id":null,"store_id":2498,"twitter":"-","website":"-","x":0,"y":0,"store_name":"Light Me Up","mall_name":"Centrio","logo_url":null,"photo_url":null,"categories":[{"id":10,"name":"Home & Appliances"}]},{"contact":"-","description":"-","facebook":"-","hours":"-","id":4917,"location":"1124-1126","mall_id":17,"map_id":null,"store_id":1004,"twitter":"-","website":"-","x":0,"y":0,"store_name":"Make Room","mall_name":"Centrio","logo_url":null,"photo_url":null,"categories":[{"id":10,"name":"Home & Appliances"}]},{"contact":"-","description":"0","facebook":"-","hours":"-","id":4919,"location":"3070-3071","mall_id":17,"map_id":null,"store_id":2499,"twitter":"-","website":"-","x":0,"y":0,"store_name":"Solidmark","mall_name":"Centrio","logo_url":null,"photo_url":null,"categories":[{"id":10,"name":"Home & Appliances"}]},{"contact":"-","description":"-","facebook":"-","hours":"-","id":4921,"location":"2018-2019","mall_id":17,"map_id":null,"store_id":241,"twitter":"-","website":"-","x":0,"y":0,"store_name":"Broadway Gems","mall_name":"Centrio","logo_url":null,"photo_url":null,"categories":[{"id":2,"name":"Apparel"},{"id":19,"name":"Hobbies/Toys/Gifts & Novelties"},{"id":11,"name":"Jewelry & Watches"}]},{"contact":"-","description":"0","facebook":"-","hours":"-","id":4924,"location":"1112","mall_id":17,"map_id":null,"store_id":2502,"twitter":"-","website":"-","x":0,"y":0,"store_name":"Claire's","mall_name":"Centrio","logo_url":null,"photo_url":null,"categories":[{"id":10,"name":"Home & Appliances"}]},{"contact":"-","description":"-","facebook":"-","hours":"-","id":4925,"location":"2027","mall_id":17,"map_id":null,"store_id":2147,"twitter":"-","website":"-","x":0,"y":0,"store_name":"Diagold","mall_name":"Centrio","logo_url":null,"photo_url":null,"categories":[{"id":11,"name":"Jewelry & Watches"}]},{"contact":"-","description":"0","facebook":"-","hours":"-","id":4926,"location":"2112","mall_id":17,"map_id":null,"store_id":614,"twitter":"-","website":"-","x":0,"y":0,"store_name":"G-Force","mall_name":"Centrio","logo_url":null,"photo_url":null,"categories":[{"id":19,"name":"Hobbies/Toys/Gifts & Novelties"}]},{"contact":"-","description":"-","facebook":"-","hours":"-","id":4928,"location":"1023","mall_id":17,"map_id":null,"store_id":1018,"twitter":"-","website":"-","x":0,"y":0,"store_name":"Marcella's","mall_name":"Centrio","logo_url":null,"photo_url":null,"categories":[{"id":2,"name":"Apparel"},{"id":19,"name":"Hobbies/Toys/Gifts & Novelties"}]},{"contact":"-","description":"0","facebook":"-","hours":"-","id":4930,"location":"1048","mall_id":17,"map_id":null,"store_id":1832,"twitter":"-","website":"-","x":0,"y":0,"store_name":"Parfois","mall_name":"Centrio","logo_url":null,"photo_url":null,"categories":[{"id":2,"name":"Apparel"}]},{"contact":"-","description":"-","facebook":"-","hours":"-","id":4931,"location":"1089","mall_id":17,"map_id":null,"store_id":1257,"twitter":"-","website":"-","x":0,"y":0,"store_name":"Philip Stein","mall_name":"Centrio","logo_url":null,"photo_url":null,"categories":[{"id":11,"name":"Jewelry & Watches"}]},{"contact":"-","description":"0","facebook":"-","hours":"-","id":4934,"location":"3012","mall_id":17,"map_id":null,"store_id":2505,"twitter":"-","website":"-","x":0,"y":0,"store_name":"Suarez Wedding Rings","mall_name":"Centrio","logo_url":null,"photo_url":null,"categories":[{"id":11,"name":"Jewelry & Watches"}]},{"contact":"-","description":"-","facebook":"-","hours":"-","id":4935,"location":"1113","mall_id":17,"map_id":null,"store_id":1889,"twitter":"-","website":"-","x":0,"y":0,"store_name":"Sunglass Hut","mall_name":"Centrio","logo_url":null,"photo_url":null,"categories":[{"id":19,"name":"Hobbies/Toys/Gifts & Novelties"},{"id":11,"name":"Jewelry & Watches"}]},{"contact":"-","description":"-","facebook":"-","hours":"-","id":4937,"location":"1063","mall_id":17,"map_id":null,"store_id":1854,"twitter":"-","website":"-","x":0,"y":0,"store_name":"Tempus","mall_name":"Centrio","logo_url":null,"photo_url":null,"categories":[{"id":11,"name":"Jewelry & Watches"}]},{"contact":"-","description":"-","facebook":"-","hours":"-","id":4938,"location":"2092","mall_id":17,"map_id":null,"store_id":1660,"twitter":"-","website":"-","x":0,"y":0,"store_name":"Time Depot","mall_name":"Centrio","logo_url":null,"photo_url":null,"categories":[{"id":11,"name":"Jewelry & Watches"}]},{"contact":"-","description":"-","facebook":"-","hours":"-","id":4939,"location":"1027","mall_id":17,"map_id":null,"store_id":1663,"twitter":"-","website":"-","x":0,"y":0,"store_name":"Timex","mall_name":"Centrio","logo_url":null,"photo_url":null,"categories":[{"id":11,"name":"Jewelry & Watches"}]},{"contact":"-","description":"-","facebook":"-","hours":"-","id":4941,"location":"2133","mall_id":17,"map_id":null,"store_id":2508,"twitter":"-","website":"-","x":0,"y":0,"store_name":"Treasures","mall_name":"Centrio","logo_url":null,"photo_url":null,"categories":[{"id":11,"name":"Jewelry & Watches"}]},{"contact":"-","description":"-","facebook":"-","hours":"-","id":4942,"location":"1049","mall_id":17,"map_id":null,"store_id":1771,"twitter":"-","website":"-","x":0,"y":0,"store_name":"Watch Republic","mall_name":"Centrio","logo_url":null,"photo_url":null,"categories":[{"id":11,"name":"Jewelry & Watches"}]},{"contact":"-","description":"-","facebook":"-","hours":"-","id":4944,"location":"1090","mall_id":17,"map_id":null,"store_id":1795,"twitter":"-","website":"-","x":0,"y":0,"store_name":"Wrist Pod","mall_name":"Centrio","logo_url":null,"photo_url":null,"categories":[{"id":22,"name":"Computers/Electronics/Communication"}]},{"contact":"-","description":"-","facebook":"-","hours":"-","id":4945,"location":"1008 - 1009","mall_id":17,"map_id":null,"store_id":92,"twitter":"-","website":"-","x":0,"y":0,"store_name":"Astrovision","mall_name":"Centrio","logo_url":null,"photo_url":null,"categories":[{"id":12,"name":"Music & Video"}]},{"contact":"-","description":"-","facebook":"-","hours":"-","id":4946,"location":"2100","mall_id":17,"map_id":null,"store_id":2319,"twitter":"-","website":"-","x":0,"y":0,"store_name":"CRESCENDO","mall_name":"Centrio","logo_url":null,"photo_url":null,"categories":[{"id":12,"name":"Music & Video"}]},{"contact":"-","description":"-","facebook":"-","hours":"-","id":4947,"location":"2077","mall_id":17,"map_id":null,"store_id":1859,"twitter":"-","website":"-","x":0,"y":0,"store_name":"JB Music","mall_name":"Centrio","logo_url":null,"photo_url":null,"categories":[{"id":12,"name":"Music & Video"}]},{"contact":"-","description":"-","facebook":"--","hours":"-","id":4948,"location":"2096","mall_id":17,"map_id":null,"store_id":1861,"twitter":"-","website":"-","x":0,"y":0,"store_name":"Delos Reyes Optical","mall_name":"Centrio","logo_url":null,"photo_url":null,"categories":[{"id":13,"name":"Optical Shops"}]},{"contact":"-","description":"-","facebook":"-","hours":"-","id":4951,"location":"2029","mall_id":17,"map_id":null,"store_id":520,"twitter":"-","website":"-","x":0,"y":0,"store_name":"Executive Optical","mall_name":"Centrio","logo_url":null,"photo_url":null,"categories":[{"id":13,"name":"Optical Shops"}]},{"contact":"-","description":"-","facebook":"-","hours":"-","id":4952,"location":"2014-2015","mall_id":17,"map_id":null,"store_id":781,"twitter":"-","website":"-","x":0,"y":0,"store_name":"Ideal Vision","mall_name":"Centrio","logo_url":null,"photo_url":null,"categories":[{"id":13,"name":"Optical Shops"}]},{"contact":"-","description":"-","facebook":"-","hours":"-","id":4955,"location":"3079","mall_id":17,"map_id":null,"store_id":2511,"twitter":"-","website":"-","x":0,"y":0,"store_name":"St. Jude Optical","mall_name":"Centrio","logo_url":null,"photo_url":null,"categories":[{"id":13,"name":"Optical Shops"}]},{"contact":"-","description":"-","facebook":"-","hours":"-","id":4956,"location":"2089","mall_id":17,"map_id":null,"store_id":2236,"twitter":"-","website":"-","x":0,"y":0,"store_name":"The Opticians","mall_name":"Centrio","logo_url":null,"photo_url":null,"categories":[{"id":13,"name":"Optical Shops"}]},{"contact":"-","description":"0","facebook":"-","hours":"-","id":4957,"location":"2064","mall_id":17,"map_id":null,"store_id":374,"twitter":"-","website":"-","x":0,"y":0,"store_name":"Colours Foto","mall_name":"Centrio","logo_url":null,"photo_url":null,"categories":[{"id":16,"name":"Photo Developing"}]},{"contact":"-","description":"-","facebook":"-","hours":"-","id":4960,"location":"3117","mall_id":17,"map_id":null,"store_id":2514,"twitter":"-","website":"-","x":0,"y":0,"store_name":"Nikon Hub","mall_name":"Centrio","logo_url":null,"photo_url":null,"categories":[{"id":16,"name":"Photo Developing"}]},{"contact":"-","description":"-","facebook":"-","hours":"-","id":4961,"location":"3091","mall_id":17,"map_id":null,"store_id":1266,"twitter":"-","website":"-","x":0,"y":0,"store_name":"Photoline","mall_name":"Centrio","logo_url":null,"photo_url":null,"categories":[{"id":16,"name":"Photo Developing"}]},{"contact":"-","description":"-","facebook":"-","hours":"-","id":4962,"location":"2012","mall_id":17,"map_id":null,"store_id":1274,"twitter":"-","website":"-","x":0,"y":0,"store_name":"Picture City","mall_name":"Centrio","logo_url":null,"photo_url":null,"categories":[{"id":16,"name":"Photo Developing"}]},{"contact":"-","description":"-","facebook":"-","hours":"-","id":4965,"location":"1043-1044","mall_id":17,"map_id":null,"store_id":2515,"twitter":"-","website":"-","x":0,"y":0,"store_name":"ALP","mall_name":"Centrio","logo_url":null,"photo_url":null,"categories":[{"id":17,"name":"Services"}]},{"contact":"-","description":"-","facebook":"-","hours":"-","id":4967,"location":"3011","mall_id":17,"map_id":null,"store_id":307,"twitter":"--","website":"-","x":0,"y":0,"store_name":"Cebuana Lhuillier Pera Padala","mall_name":"Centrio","logo_url":null,"photo_url":null,"categories":[{"id":17,"name":"Services"}]},{"contact":"-","description":"-","facebook":"-","hours":"-","id":4968,"location":"3019","mall_id":17,"map_id":null,"store_id":392,"twitter":"--","website":"-","x":0,"y":0,"store_name":"Core Pacific Money Exchange ","mall_name":"Centrio","logo_url":null,"photo_url":null,"categories":[]},{"contact":"-","description":"-","facebook":"-","hours":"-","id":4969,"location":"2094-2095","mall_id":17,"map_id":null,"store_id":659,"twitter":"-","website":"-","x":0,"y":0,"store_name":"Globe Telecom","mall_name":"Centrio","logo_url":null,"photo_url":null,"categories":[{"id":22,"name":"Computers/Electronics/Communication"}]},{"contact":"-","description":"-","facebook":"-","hours":"-","id":4972,"location":"3075","mall_id":17,"map_id":null,"store_id":684,"twitter":"-","website":"-","x":0,"y":0,"store_name":"Green Apple Dental","mall_name":"Centrio","logo_url":null,"photo_url":null,"categories":[]},{"contact":"-","description":"-","facebook":"-","hours":"-","id":4975,"location":"1031-1032","mall_id":17,"map_id":null,"store_id":2519,"twitter":"-","website":"-","x":0,"y":0,"store_name":"House of Travel","mall_name":"Centrio","logo_url":null,"photo_url":null,"categories":[{"id":17,"name":"Services"}]},{"contact":"-","description":"-","facebook":"-","hours":"-","id":4977,"location":"3010","mall_id":17,"map_id":null,"store_id":940,"twitter":"-","website":"-","x":0,"y":0,"store_name":"LBC ","mall_name":"Centrio","logo_url":null,"photo_url":null,"categories":[{"id":17,"name":"Services"}]},{"contact":"-","description":"-","facebook":"-","hours":"-","id":4979,"location":"3056","mall_id":17,"map_id":null,"store_id":2521,"twitter":"-","website":"-","x":0,"y":0,"store_name":"Paperworks","mall_name":"Centrio","logo_url":null,"photo_url":null,"categories":[{"id":17,"name":"Services"}]},{"contact":"-","description":"-","facebook":"-","hours":"-","id":4980,"location":"3016","mall_id":17,"map_id":null,"store_id":2522,"twitter":"--","website":"-","x":0,"y":0,"store_name":"Parasat Payment Center","mall_name":"Centrio","logo_url":null,"photo_url":null,"categories":[{"id":17,"name":"Services"}]},{"contact":"-","description":"-","facebook":"-","hours":"-","id":4981,"location":"3017","mall_id":17,"map_id":null,"store_id":2170,"twitter":"-","website":"-","x":0,"y":0,"store_name":"SST Repair Shop","mall_name":"Centrio","logo_url":null,"photo_url":null,"categories":[{"id":17,"name":"Services"}]},{"contact":"-","description":"-","facebook":"-","hours":"-","id":4982,"location":"3113","mall_id":17,"map_id":null,"store_id":1898,"twitter":"-","website":"-","x":0,"y":0,"store_name":"Sun Shop","mall_name":"Centrio","logo_url":null,"photo_url":null,"categories":[{"id":22,"name":"Computers/Electronics/Communication"}]},{"contact":"-","description":"-","facebook":"-","hours":"-","id":4983,"location":"2070","mall_id":17,"map_id":null,"store_id":2390,"twitter":"-","website":"-","x":0,"y":0,"store_name":"Adidas Original","mall_name":"Centrio","logo_url":null,"photo_url":null,"categories":[{"id":20,"name":"Sports Shops"}]},{"contact":"-","description":"-","facebook":"-","hours":"--","id":4985,"location":"1024-1025","mall_id":17,"map_id":null,"store_id":33,"twitter":"-","website":"-","x":0,"y":0,"store_name":"Alberto","mall_name":"Centrio","logo_url":null,"photo_url":null,"categories":[{"id":18,"name":"Shoes, Bags, Leather Goods"}]},{"contact":"-","description":"0","facebook":"-","hours":"-","id":4986,"location":"1093-1094","mall_id":17,"map_id":null,"store_id":34,"twitter":"-","website":"-","x":0,"y":0,"store_name":"Aldo","mall_name":"Centrio","logo_url":null,"photo_url":null,"categories":[{"id":18,"name":"Shoes, Bags, Leather Goods"}]},{"contact":"-","description":"-","facebook":"-","hours":"-","id":4987,"location":"1041","mall_id":17,"map_id":null,"store_id":142,"twitter":"-","website":"-","x":0,"y":0,"store_name":"Bambu","mall_name":"Centrio","logo_url":null,"photo_url":null,"categories":[{"id":18,"name":"Shoes, Bags, Leather Goods"},{"id":20,"name":"Sports Shops"}]},{"contact":"-","description":"-","facebook":"-","hours":"-","id":4989,"location":"2075-2076","mall_id":17,"map_id":null,"store_id":232,"twitter":"-","website":"-","x":0,"y":0,"store_name":"Bratpack","mall_name":"Centrio","logo_url":null,"photo_url":null,"categories":[{"id":18,"name":"Shoes, Bags, Leather Goods"}]},{"contact":"-","description":"-","facebook":"-","hours":"-","id":4990,"location":"1039","mall_id":17,"map_id":null,"store_id":311,"twitter":"-","website":"-","x":0,"y":0,"store_name":"Celine","mall_name":"Centrio","logo_url":null,"photo_url":null,"categories":[{"id":18,"name":"Shoes, Bags, Leather Goods"}]},{"contact":"-","description":"-","facebook":"-","hours":"-","id":4991,"location":"1038","mall_id":17,"map_id":null,"store_id":2299,"twitter":"-","website":"-","x":0,"y":0,"store_name":"Clarks","mall_name":"Centrio","logo_url":null,"photo_url":null,"categories":[{"id":18,"name":"Shoes, Bags, Leather Goods"}]},{"contact":"-","description":"-","facebook":"-","hours":"-","id":4992,"location":"2073-2074","mall_id":17,"map_id":null,"store_id":388,"twitter":"-","website":"-","x":0,"y":0,"store_name":"Converse","mall_name":"Centrio","logo_url":null,"photo_url":null,"categories":[{"id":2,"name":"Apparel"},{"id":18,"name":"Shoes, Bags, Leather Goods"},{"id":20,"name":"Sports Shops"}]},{"contact":"-","description":"-","facebook":"-","hours":"-","id":4993,"location":"2130","mall_id":17,"map_id":null,"store_id":404,"twitter":"-","website":"-","x":0,"y":0,"store_name":"Crocs","mall_name":"Centrio","logo_url":null,"photo_url":null,"categories":[{"id":18,"name":"Shoes, Bags, Leather Goods"}]},{"contact":"-","description":"-","facebook":"-","hours":"-","id":4994,"location":"2131","mall_id":17,"map_id":null,"store_id":412,"twitter":"-","website":"-","x":0,"y":0,"store_name":"Cushe","mall_name":"Centrio","logo_url":null,"photo_url":null,"categories":[{"id":18,"name":"Shoes, Bags, Leather Goods"}]},{"contact":"-","description":"-","facebook":"-","hours":"-","id":4995,"location":"1073-1076","mall_id":17,"map_id":null,"store_id":1879,"twitter":"-","website":"-","x":0,"y":0,"store_name":"DC Shoes","mall_name":"Centrio","logo_url":null,"photo_url":null,"categories":[{"id":18,"name":"Shoes, Bags, Leather Goods"}]},{"contact":"-","description":"-","facebook":"-","hours":"-","id":4996,"location":"1064-1065","mall_id":17,"map_id":null,"store_id":644,"twitter":"-","website":"-","x":0,"y":0,"store_name":"Geox","mall_name":"Centrio","logo_url":null,"photo_url":null,"categories":[{"id":18,"name":"Shoes, Bags, Leather Goods"}]},{"contact":"-","description":"-","facebook":"-","hours":"-","id":4997,"location":"1035","mall_id":17,"map_id":null,"store_id":765,"twitter":"-","website":"-","x":0,"y":0,"store_name":"Hush Puppies","mall_name":"Centrio","logo_url":null,"photo_url":null,"categories":[{"id":18,"name":"Shoes, Bags, Leather Goods"}]},{"contact":"-","description":"-","facebook":"-","hours":"-","id":4998,"location":"2115","mall_id":17,"map_id":null,"store_id":2524,"twitter":"-","website":"-","x":0,"y":0,"store_name":"Kipling","mall_name":"Centrio","logo_url":null,"photo_url":null,"categories":[{"id":18,"name":"Shoes, Bags, Leather Goods"}]},{"contact":"-","description":"-","facebook":"-","hours":"-","id":4999,"location":"2028","mall_id":17,"map_id":null,"store_id":943,"twitter":"-","website":"-","x":0,"y":0,"store_name":"Leaveland","mall_name":"Centrio","logo_url":null,"photo_url":null,"categories":[{"id":18,"name":"Shoes, Bags, Leather Goods"}]},{"contact":"-","description":"-","facebook":"-","hours":"-","id":5000,"location":"2046-2047","mall_id":17,"map_id":null,"store_id":1841,"twitter":"-","website":"-","x":0,"y":0,"store_name":"Mags","mall_name":"Centrio","logo_url":null,"photo_url":null,"categories":[{"id":2,"name":"Apparel"}]},{"contact":"-","description":"-","facebook":"-","hours":"-","id":5001,"location":"1033-1034","mall_id":17,"map_id":null,"store_id":1048,"twitter":"-","website":"-","x":0,"y":0,"store_name":"Mendrez","mall_name":"Centrio","logo_url":null,"photo_url":null,"categories":[{"id":18,"name":"Shoes, Bags, Leather Goods"}]},{"contact":"-","description":"-","facebook":"-","hours":"-","id":5002,"location":"2154","mall_id":17,"map_id":null,"store_id":1053,"twitter":"-","website":"-","x":0,"y":0,"store_name":"Merrell","mall_name":"Centrio","logo_url":null,"photo_url":null,"categories":[{"id":18,"name":"Shoes, Bags, Leather Goods"},{"id":20,"name":"Sports Shops"}]},{"contact":"-","description":"-","facebook":"-","hours":"-","id":5003,"location":"2082","mall_id":17,"map_id":null,"store_id":2072,"twitter":"-","website":"-","x":0,"y":0,"store_name":"Nike","mall_name":"Centrio","logo_url":null,"photo_url":null,"categories":[{"id":2,"name":"Apparel"},{"id":18,"name":"Shoes, Bags, Leather Goods"},{"id":20,"name":"Sports Shops"}]},{"contact":"-","description":"-","facebook":"-","hours":"-","id":5005,"location":"2041-2042","mall_id":17,"map_id":null,"store_id":2241,"twitter":"-","website":"-","x":0,"y":0,"store_name":"Officine","mall_name":"Centrio","logo_url":null,"photo_url":null,"categories":[{"id":18,"name":"Shoes, Bags, Leather Goods"}]},{"contact":"-","description":"-","facebook":"-","hours":"-","id":5006,"location":"1115-1118","mall_id":17,"map_id":null,"store_id":1225,"twitter":"-","website":"-","x":0,"y":0,"store_name":"Payless Shoe Source","mall_name":"Centrio","logo_url":null,"photo_url":null,"categories":[{"id":18,"name":"Shoes, Bags, Leather Goods"}]},{"contact":"-","description":"-","facebook":"-","hours":"-","id":5007,"location":"2048","mall_id":17,"map_id":null,"store_id":2217,"twitter":"-","website":"-","x":0,"y":0,"store_name":"Primadonna","mall_name":"Centrio","logo_url":null,"photo_url":null,"categories":[{"id":2,"name":"Apparel"}]},{"contact":"-","description":"-","facebook":"-","hours":"-","id":5008,"location":"2127","mall_id":17,"map_id":null,"store_id":1323,"twitter":"-","website":"-","x":0,"y":0,"store_name":"Puma","mall_name":"Centrio","logo_url":null,"photo_url":null,"categories":[{"id":18,"name":"Shoes, Bags, Leather Goods"},{"id":20,"name":"Sports Shops"}]},{"contact":"-","description":"-","facebook":"-","hours":"-","id":5009,"location":"1082-1083","mall_id":17,"map_id":null,"store_id":1363,"twitter":"-","website":"-","x":0,"y":0,"store_name":"ResToeRun","mall_name":"Centrio","logo_url":null,"photo_url":null,"categories":[{"id":18,"name":"Shoes, Bags, Leather Goods"}]},{"contact":"-","description":"-","facebook":"-","hours":"-","id":5010,"location":"2128","mall_id":17,"map_id":null,"store_id":1379,"twitter":"-","website":"-","x":0,"y":0,"store_name":"Rockport","mall_name":"Centrio","logo_url":null,"photo_url":null,"categories":[{"id":18,"name":"Shoes, Bags, Leather Goods"}]},{"contact":"-","description":"-","facebook":"-","hours":"-","id":5011,"location":"2106","mall_id":17,"map_id":null,"store_id":2526,"twitter":"-","website":"-","x":0,"y":0,"store_name":"Sandugo","mall_name":"Centrio","logo_url":null,"photo_url":null,"categories":[{"id":18,"name":"Shoes, Bags, Leather Goods"}]},{"contact":"-","description":"-","facebook":"-","hours":"-","id":5012,"location":"2081","mall_id":17,"map_id":null,"store_id":1422,"twitter":"-","website":"-","x":0,"y":0,"store_name":"Sanuk","mall_name":"Centrio","logo_url":null,"photo_url":null,"categories":[{"id":18,"name":"Shoes, Bags, Leather Goods"},{"id":20,"name":"Sports Shops"}]},{"contact":"-","description":"-","facebook":"-","hours":"-","id":5013,"location":"1066","mall_id":17,"map_id":null,"store_id":1438,"twitter":"-","website":"-","x":0,"y":0,"store_name":"Sebago","mall_name":"Centrio","logo_url":null,"photo_url":null,"categories":[{"id":18,"name":"Shoes, Bags, Leather Goods"}]},{"contact":"-","description":"-","facebook":"-","hours":"-","id":5014,"location":"2119-2120","mall_id":17,"map_id":null,"store_id":1460,"twitter":"-","website":"-","x":0,"y":0,"store_name":"Shoe Salon","mall_name":"Centrio","logo_url":null,"photo_url":null,"categories":[{"id":18,"name":"Shoes, Bags, Leather Goods"},{"id":20,"name":"Sports Shops"}]},{"contact":"-","description":"-","facebook":"-","hours":"-","id":5015,"location":"2020","mall_id":17,"map_id":null,"store_id":1885,"twitter":"-","website":"-","x":0,"y":0,"store_name":"Shoebox","mall_name":"Centrio","logo_url":null,"photo_url":null,"categories":[{"id":18,"name":"Shoes, Bags, Leather Goods"}]},{"contact":"-","description":"-","facebook":"-","hours":"-","id":5017,"location":"2123-2124","mall_id":17,"map_id":null,"store_id":1481,"twitter":"-","website":"-","x":0,"y":0,"store_name":"Skechers","mall_name":"Centrio","logo_url":null,"photo_url":null,"categories":[{"id":18,"name":"Shoes, Bags, Leather Goods"},{"id":20,"name":"Sports Shops"}]},{"contact":"-","description":"-","facebook":"-","hours":"-","id":5018,"location":"1050","mall_id":17,"map_id":null,"store_id":2242,"twitter":"-","website":"-","x":0,"y":0,"store_name":"Sperry","mall_name":"Centrio","logo_url":null,"photo_url":null,"categories":[{"id":18,"name":"Shoes, Bags, Leather Goods"}]},{"contact":"-","description":"-","facebook":"-","hours":"-","id":5019,"location":"2125-2126","mall_id":17,"map_id":null,"store_id":2530,"twitter":"-","website":"-","x":0,"y":0,"store_name":"Spruce","mall_name":"Centrio","logo_url":null,"photo_url":null,"categories":[{"id":18,"name":"Shoes, Bags, Leather Goods"}]},{"contact":"-","description":"-","facebook":"-","hours":"-","id":5021,"location":"2043","mall_id":17,"map_id":null,"store_id":2531,"twitter":"-","website":"-","x":0,"y":0,"store_name":"The Give Project","mall_name":"Centrio","logo_url":null,"photo_url":null,"categories":[{"id":18,"name":"Shoes, Bags, Leather Goods"}]},{"contact":"-","description":"-","facebook":"-","hours":"-","id":5022,"location":"2110-2111","mall_id":17,"map_id":null,"store_id":1644,"twitter":"-","website":"-","x":0,"y":0,"store_name":"The Travel Club","mall_name":"Centrio","logo_url":null,"photo_url":null,"categories":[{"id":18,"name":"Shoes, Bags, Leather Goods"}]},{"contact":"-","description":"-","facebook":"-","hours":"-","id":5023,"location":"2113-2114","mall_id":17,"map_id":null,"store_id":1735,"twitter":"-","website":"-","x":0,"y":0,"store_name":"Vans","mall_name":"Centrio","logo_url":null,"photo_url":null,"categories":[{"id":2,"name":"Apparel"},{"id":18,"name":"Shoes, Bags, Leather Goods"},{"id":20,"name":"Sports Shops"}]},{"contact":"-","description":"-","facebook":"-","hours":"-","id":5024,"location":"3003","mall_id":17,"map_id":null,"store_id":377,"twitter":"-","website":"-","x":0,"y":0,"store_name":"Comic Alley","mall_name":"Centrio","logo_url":null,"photo_url":null,"categories":[{"id":19,"name":"Hobbies/Toys/Gifts & Novelties"}]},{"contact":"-","description":"-","facebook":"-","hours":"-","id":5025,"location":"2035","mall_id":17,"map_id":null,"store_id":706,"twitter":"-","website":"-","x":0,"y":0,"store_name":"Hannah's","mall_name":"Centrio","logo_url":null,"photo_url":null,"categories":[{"id":19,"name":"Hobbies/Toys/Gifts & Novelties"}]},{"contact":"-","description":"-","facebook":"-","hours":"-","id":5026,"location":"2065-2066","mall_id":17,"map_id":null,"store_id":347,"twitter":"-","website":"-","x":0,"y":0,"store_name":"Chris Sports","mall_name":"Centrio","logo_url":null,"photo_url":null,"categories":[{"id":20,"name":"Sports Shops"}]},{"contact":"-","description":"-","facebook":"-","hours":"-","id":5051,"location":"2091","mall_id":17,"map_id":null,"store_id":841,"twitter":"-","website":"-","x":0,"y":0,"store_name":"Juego","mall_name":"Centrio","logo_url":null,"photo_url":null,"categories":[{"id":20,"name":"Sports Shops"}]},{"contact":"-","description":"-","facebook":"-","hours":"-","id":5053,"location":"2078-2080","mall_id":17,"map_id":null,"store_id":1185,"twitter":"-","website":"-","x":0,"y":0,"store_name":"Olympic Village","mall_name":"Centrio","logo_url":null,"photo_url":null,"categories":[{"id":20,"name":"Sports Shops"}]},{"contact":"-","description":"-","facebook":"-","hours":"-","id":5055,"location":"2061-2062","mall_id":17,"map_id":null,"store_id":1288,"twitter":"-","website":"-","x":0,"y":0,"store_name":"Planet Sports","mall_name":"Centrio","logo_url":null,"photo_url":null,"categories":[{"id":20,"name":"Sports Shops"}]},{"contact":"-","description":"-","facebook":"-","hours":"-","id":5056,"location":"2121","mall_id":17,"map_id":null,"store_id":1517,"twitter":"-","website":"-","x":0,"y":0,"store_name":"Speedo","mall_name":"Centrio","logo_url":null,"photo_url":null,"categories":[{"id":20,"name":"Sports Shops"}]},{"contact":"-","description":"-","facebook":"-","hours":"-","id":5059,"location":"2084","mall_id":17,"map_id":null,"store_id":1674,"twitter":"-","website":"-","x":0,"y":0,"store_name":"Toby's Sports","mall_name":"Centrio","logo_url":null,"photo_url":null,"categories":[{"id":20,"name":"Sports Shops"}]},{"contact":"-","description":"-","facebook":"--","hours":"-","id":5061,"location":"-","mall_id":17,"map_id":null,"store_id":1404,"twitter":"-","website":"-","x":0,"y":0,"store_name":"Rustans Supermarket","mall_name":"Centrio","logo_url":null,"photo_url":null,"categories":[{"id":21,"name":"Supermarket/Hypermarket"}]},{"contact":"-","description":"0","facebook":"-","hours":"-","id":5062,"location":"2122-2157","mall_id":17,"map_id":null,"store_id":212,"twitter":"-","website":"-","x":0,"y":0,"store_name":"Bo's Coffee","mall_name":"Centrio","logo_url":null,"photo_url":null,"categories":[{"id":24,"name":"Cafe/Bakeshops/Desserts"}]},{"contact":"-","description":"-","facebook":"-","hours":"-","id":5065,"location":"1154-1155","mall_id":17,"map_id":null,"store_id":237,"twitter":"-","website":"-","x":0,"y":0,"store_name":"Bread Talk","mall_name":"Centrio","logo_url":null,"photo_url":null,"categories":[{"id":24,"name":"Cafe/Bakeshops/Desserts"}]},{"contact":"-","description":"-","facebook":"-","hours":"-","id":5066,"location":"3036","mall_id":17,"map_id":null,"store_id":368,"twitter":"-","website":"-","x":0,"y":0,"store_name":"Coffee Dream","mall_name":"Centrio","logo_url":null,"photo_url":null,"categories":[{"id":27,"name":"Food Court"}]},{"contact":"-","description":"-","facebook":"-","hours":"-","id":5067,"location":"1148","mall_id":17,"map_id":null,"store_id":2397,"twitter":"-","website":"-","x":0,"y":0,"store_name":"Coffee Bean and Tea Leaf","mall_name":"Centrio","logo_url":null,"photo_url":null,"categories":[{"id":24,"name":"Cafe/Bakeshops/Desserts"}]},{"contact":"-","description":"-","facebook":"-","hours":"-","id":5070,"location":"2156 / Ground Floor","mall_id":17,"map_id":null,"store_id":486,"twitter":"-","website":"-","x":0,"y":0,"store_name":"Dunkin Donuts","mall_name":"Centrio","logo_url":null,"photo_url":null,"categories":[{"id":28,"name":"Food Stalls/Carts"}]},{"contact":"-","description":"-","facebook":"-","hours":"-","id":5072,"location":"2155","mall_id":17,"map_id":null,"store_id":603,"twitter":"-","website":"-","x":0,"y":0,"store_name":"Fruits In Ice Cream","mall_name":"Centrio","logo_url":null,"photo_url":null,"categories":[{"id":28,"name":"Food Stalls/Carts"}]},{"contact":"-","description":"-","facebook":"-","hours":"-","id":5073,"location":"1007","mall_id":17,"map_id":null,"store_id":671,"twitter":"-","website":"-","x":0,"y":0,"store_name":"Goldilocks","mall_name":"Centrio","logo_url":null,"photo_url":null,"categories":[{"id":24,"name":"Cafe/Bakeshops/Desserts"}]},{"contact":"-","description":"-","facebook":"-","hours":"-","id":5074,"location":"2153","mall_id":17,"map_id":null,"store_id":2406,"twitter":"-","website":"-","x":0,"y":0,"store_name":"Happy Lemon","mall_name":"Centrio","logo_url":null,"photo_url":null,"categories":[{"id":24,"name":"Cafe/Bakeshops/Desserts"}]},{"contact":"-","description":"-","facebook":"-","hours":"-","id":5075,"location":"1140","mall_id":17,"map_id":null,"store_id":2108,"twitter":"-","website":"-","x":0,"y":0,"store_name":"J.Co","mall_name":"Centrio","logo_url":null,"photo_url":null,"categories":[{"id":24,"name":"Cafe/Bakeshops/Desserts"}]},{"contact":"-","description":"-","facebook":"-","hours":"-","id":5076,"location":"1140","mall_id":17,"map_id":null,"store_id":2108,"twitter":"-","website":"-","x":0,"y":0,"store_name":"J.Co","mall_name":"Centrio","logo_url":null,"photo_url":null,"categories":[{"id":24,"name":"Cafe/Bakeshops/Desserts"}]},{"contact":"-","description":"-","facebook":"-","hours":"-","id":5081,"location":"3030-3031","mall_id":17,"map_id":null,"store_id":2555,"twitter":"-","website":"-","x":0,"y":0,"store_name":"Nai Cha","mall_name":"Centrio","logo_url":null,"photo_url":null,"categories":[{"id":24,"name":"Cafe/Bakeshops/Desserts"}]},{"contact":"-","description":"-","facebook":"-","hours":"-","id":5082,"location":"1010","mall_id":17,"map_id":null,"store_id":1353,"twitter":"-","website":"-","x":0,"y":0,"store_name":"Red Ribbon","mall_name":"Centrio","logo_url":null,"photo_url":null,"categories":[{"id":24,"name":"Cafe/Bakeshops/Desserts"}]},{"contact":"-","description":"-","facebook":"-","hours":"-","id":5083,"location":"1138-1139","mall_id":17,"map_id":null,"store_id":1531,"twitter":"-","website":"-","x":0,"y":0,"store_name":"Starbucks","mall_name":"Centrio","logo_url":null,"photo_url":null,"categories":[{"id":24,"name":"Cafe/Bakeshops/Desserts"}]},{"contact":"-","description":"-","facebook":"-","hours":"-","id":5084,"location":"1158","mall_id":17,"map_id":null,"store_id":1786,"twitter":"-","website":"-","x":0,"y":0,"store_name":"White Hat","mall_name":"Centrio","logo_url":null,"photo_url":null,"categories":[{"id":24,"name":"Cafe/Bakeshops/Desserts"}]},{"contact":"-","description":"-","facebook":"-","hours":"-","id":5085,"location":"3035","mall_id":17,"map_id":null,"store_id":2556,"twitter":"-","website":"-","x":0,"y":0,"store_name":"Barkadahan Grill","mall_name":"Centrio","logo_url":null,"photo_url":null,"categories":[{"id":25,"name":"Restaurants/Bars"}]},{"contact":"-","description":"-","facebook":"-","hours":"-","id":5086,"location":"1149-1150","mall_id":17,"map_id":null,"store_id":189,"twitter":"-","website":"-","x":0,"y":0,"store_name":"Bigby's","mall_name":"Centrio","logo_url":null,"photo_url":null,"categories":[{"id":25,"name":"Restaurants/Bars"}]},{"contact":"-","description":"-","facebook":"-","hours":"-","id":5087,"location":"1145","mall_id":17,"map_id":null,"store_id":2135,"twitter":"-","website":"-","x":0,"y":0,"store_name":"Bulgogi Bros.","mall_name":"Centrio","logo_url":null,"photo_url":null,"categories":[{"id":25,"name":"Restaurants/Bars"}]},{"contact":"-","description":"-","facebook":"-","hours":"-","id":5088,"location":"1151-1152","mall_id":17,"map_id":null,"store_id":2557,"twitter":"-","website":"-","x":0,"y":0,"store_name":"Candy's","mall_name":"Centrio","logo_url":null,"photo_url":null,"categories":[{"id":25,"name":"Restaurants/Bars"}]},{"contact":"-","description":"-","facebook":"-","hours":"-","id":5089,"location":"3047","mall_id":17,"map_id":null,"store_id":358,"twitter":"-","website":"-","x":0,"y":0,"store_name":"Classic Savory","mall_name":"Centrio","logo_url":null,"photo_url":null,"categories":[{"id":25,"name":"Restaurants/Bars"}]},{"contact":"-","description":"-","facebook":"-","hours":"-","id":5090,"location":"3039","mall_id":17,"map_id":null,"store_id":2558,"twitter":"-","website":"-","x":0,"y":0,"store_name":"Delecta","mall_name":"Centrio","logo_url":null,"photo_url":null,"categories":[{"id":25,"name":"Restaurants/Bars"}]},{"contact":"-","description":"-","facebook":"-","hours":"-","id":5091,"location":"3040","mall_id":17,"map_id":null,"store_id":2559,"twitter":"-","website":"-","x":0,"y":0,"store_name":"Dong Juan","mall_name":"Centrio","logo_url":null,"photo_url":null,"categories":[{"id":25,"name":"Restaurants/Bars"}]},{"contact":"-","description":"-","facebook":"-","hours":"-","id":5093,"location":"2146-2147","mall_id":17,"map_id":null,"store_id":645,"twitter":"-","website":"-","x":0,"y":0,"store_name":"Gerry's Grill","mall_name":"Centrio","logo_url":null,"photo_url":null,"categories":[{"id":25,"name":"Restaurants/Bars"}]},{"contact":"-","description":"-","facebook":"-","hours":"-","id":5094,"location":"2161","mall_id":17,"map_id":null,"store_id":761,"twitter":"-","website":"-","x":0,"y":0,"store_name":"Hukad","mall_name":"Centrio","logo_url":null,"photo_url":null,"categories":[{"id":25,"name":"Restaurants/Bars"}]},{"contact":"-","description":"-","facebook":"-","hours":"-","id":5095,"location":"1143","mall_id":17,"map_id":null,"store_id":804,"twitter":"-","website":"-","x":0,"y":0,"store_name":"Italianni's","mall_name":"Centrio","logo_url":null,"photo_url":null,"categories":[{"id":25,"name":"Restaurants/Bars"}]},{"contact":"-","description":"-","facebook":"-","hours":"-","id":5096,"location":"3045 - 3109","mall_id":17,"map_id":null,"store_id":1938,"twitter":"-","website":"-","x":0,"y":0,"store_name":"Mandarin Tea Garden","mall_name":"Centrio","logo_url":null,"photo_url":null,"categories":[{"id":25,"name":"Restaurants/Bars"}]},{"contact":"-","description":"-","facebook":"-","hours":"-","id":5097,"location":"1146-1147","mall_id":17,"map_id":null,"store_id":2404,"twitter":"-","website":"-","x":0,"y":0,"store_name":"Mesa","mall_name":"Centrio","logo_url":null,"photo_url":null,"categories":[{"id":25,"name":"Restaurants/Bars"}]},{"contact":"-","description":"-","facebook":"-","hours":"-","id":5098,"location":"2160","mall_id":17,"map_id":null,"store_id":1092,"twitter":"-","website":"-","x":0,"y":0,"store_name":"Mooon Cafe","mall_name":"Centrio","logo_url":null,"photo_url":null,"categories":[{"id":24,"name":"Cafe/Bakeshops/Desserts"}]},{"contact":"-","description":"-","facebook":"-","hours":"-","id":5099,"location":"2151","mall_id":17,"map_id":null,"store_id":1210,"twitter":"-","website":"-","x":0,"y":0,"store_name":"Pancake House","mall_name":"Centrio","logo_url":null,"photo_url":null,"categories":[{"id":25,"name":"Restaurants/Bars"}]},{"contact":"-","description":"-","facebook":"-","hours":"-","id":5100,"location":"3046","mall_id":17,"map_id":null,"store_id":2561,"twitter":"-","website":"-","x":0,"y":0,"store_name":"Roadhouse Cafe","mall_name":"Centrio","logo_url":null,"photo_url":null,"categories":[{"id":25,"name":"Restaurants/Bars"}]},{"contact":"-","description":"-","facebook":"-","hours":"-","id":5101,"location":"2144-2145","mall_id":17,"map_id":null,"store_id":2262,"twitter":"-","website":"-","x":0,"y":0,"store_name":"Seafood Island","mall_name":"Centrio","logo_url":null,"photo_url":null,"categories":[{"id":25,"name":"Restaurants/Bars"}]},{"contact":"-","description":"-","facebook":"-","hours":"-","id":5102,"location":"2152","mall_id":17,"map_id":null,"store_id":1553,"twitter":"-","website":"-","x":0,"y":0,"store_name":"Sumo Sam","mall_name":"Centrio","logo_url":null,"photo_url":null,"categories":[{"id":25,"name":"Restaurants/Bars"}]},{"contact":"-","description":"-","facebook":"-","hours":"-","id":5103,"location":"3049 - 3050","mall_id":17,"map_id":null,"store_id":1556,"twitter":"-","website":"-","x":0,"y":0,"store_name":"Sunburst","mall_name":"Centrio","logo_url":null,"photo_url":null,"categories":[{"id":25,"name":"Restaurants/Bars"}]},{"contact":"-","description":"-","facebook":"-","hours":"-","id":5104,"location":"1120 -1144","mall_id":17,"map_id":null,"store_id":1612,"twitter":"-","website":"-","x":0,"y":0,"store_name":"TGI Friday's","mall_name":"Centrio","logo_url":null,"photo_url":null,"categories":[{"id":25,"name":"Restaurants/Bars"}]},{"contact":"-","description":"-","facebook":"-","hours":"-","id":5106,"location":"1153","mall_id":17,"map_id":null,"store_id":2562,"twitter":"-","website":"-","x":0,"y":0,"store_name":"Thai Me Up","mall_name":"Centrio","logo_url":null,"photo_url":null,"categories":[{"id":25,"name":"Restaurants/Bars"}]},{"contact":"-","description":"-","facebook":"-","hours":"-","id":5107,"location":"3033 - 3034","mall_id":17,"map_id":null,"store_id":2325,"twitter":"-","website":"-","x":0,"y":0,"store_name":"TOKYO BUBBLE TEA","mall_name":"Centrio","logo_url":null,"photo_url":null,"categories":[{"id":25,"name":"Restaurants/Bars"}]},{"contact":"-","description":"-","facebook":"-","hours":"-","id":5108,"location":"2158","mall_id":17,"map_id":null,"store_id":81,"twitter":"-","website":"-","x":0,"y":0,"store_name":"Army Navy","mall_name":"Centrio","logo_url":null,"photo_url":null,"categories":[{"id":25,"name":"Restaurants/Bars"}]},{"contact":"-","description":"-","facebook":"-","hours":"-","id":5109,"location":"1054-1056","mall_id":17,"map_id":null,"store_id":346,"twitter":"-","website":"-","x":0,"y":0,"store_name":"Chowking","mall_name":"Centrio","logo_url":null,"photo_url":null,"categories":[{"id":26,"name":"Fastfood"}]},{"contact":"-","description":"-","facebook":"-","hours":"-","id":5110,"location":"2003-2005","mall_id":17,"map_id":null,"store_id":1946,"twitter":"-","website":"-","x":0,"y":0,"store_name":"Greenwich","mall_name":"Centrio","logo_url":null,"photo_url":null,"categories":[{"id":26,"name":"Fastfood"}]},{"contact":"-","description":"-","facebook":"-","hours":"-","id":5111,"location":"1160-2002","mall_id":17,"map_id":null,"store_id":837,"twitter":"-","website":"-","x":0,"y":0,"store_name":"Jollibee","mall_name":"Centrio","logo_url":null,"photo_url":null,"categories":[{"id":26,"name":"Fastfood"}]},{"contact":"-","description":"-","facebook":"-","hours":"-","id":5112,"location":"1159, 2058-2059","mall_id":17,"map_id":null,"store_id":2538,"twitter":"-","website":"-","x":0,"y":0,"store_name":"KFC","mall_name":"Centrio","logo_url":null,"photo_url":null,"categories":[{"id":26,"name":"Fastfood"}]},{"contact":"-","description":"--","facebook":"-","hours":"-","id":5113,"location":"2007-2009","mall_id":17,"map_id":null,"store_id":1947,"twitter":"-","website":"-","x":0,"y":0,"store_name":"Mang Inasal","mall_name":"Centrio","logo_url":null,"photo_url":null,"categories":[{"id":26,"name":"Fastfood"}]},{"contact":"-","description":"-","facebook":"-","hours":"-","id":5114,"location":"1003, 1005-1006,2006","mall_id":17,"map_id":null,"store_id":1038,"twitter":"-","website":"-","x":0,"y":0,"store_name":"McDonald's","mall_name":"Centrio","logo_url":null,"photo_url":null,"categories":[{"id":26,"name":"Fastfood"}]},{"contact":"-","description":"-","facebook":"-","hours":"-","id":5115,"location":"3028","mall_id":17,"map_id":null,"store_id":2563,"twitter":"-","website":"-","x":0,"y":0,"store_name":"Oro Shawarma","mall_name":"Centrio","logo_url":null,"photo_url":null,"categories":[{"id":26,"name":"Fastfood"}]},{"contact":"-","description":"-","facebook":"-","hours":"-","id":5116,"location":"3027","mall_id":17,"map_id":null,"store_id":1301,"twitter":"-","website":"-","x":0,"y":0,"store_name":"Potato Corner","mall_name":"Centrio","logo_url":null,"photo_url":null,"categories":[{"id":27,"name":"Food Court"}]},{"contact":"-","description":"-","facebook":"-","hours":"-","id":5117,"location":"2150","mall_id":17,"map_id":null,"store_id":1428,"twitter":"--","website":"-","x":0,"y":0,"store_name":"Sbarro","mall_name":"Centrio","logo_url":null,"photo_url":null,"categories":[{"id":26,"name":"Fastfood"}]},{"contact":"-","description":"-","facebook":"-","hours":"-","id":5118,"location":"3029","mall_id":17,"map_id":null,"store_id":2564,"twitter":"-","website":"-","x":0,"y":0,"store_name":"Taco Bistro","mall_name":"Centrio","logo_url":null,"photo_url":null,"categories":[{"id":26,"name":"Fastfood"}]},{"contact":"-","description":"-","facebook":"-","hours":"-","id":5119,"location":"3032","mall_id":17,"map_id":null,"store_id":1594,"twitter":"-","website":"-","x":0,"y":0,"store_name":"Taters","mall_name":"Centrio","logo_url":null,"photo_url":null,"categories":[{"id":26,"name":"Fastfood"}]},{"contact":"-","description":"--","facebook":"-","hours":"-","id":5120,"location":"2159","mall_id":17,"map_id":null,"store_id":1804,"twitter":"-","website":"-","x":0,"y":0,"store_name":"Yellow Cab","mall_name":"Centrio","logo_url":null,"photo_url":null,"categories":[{"id":25,"name":"Restaurants/Bars"}]},{"contact":"-","description":"-","facebook":"-","hours":"-","id":5121,"location":"Ground Floor","mall_id":17,"map_id":null,"store_id":91,"twitter":"--","website":"-","x":0,"y":0,"store_name":"Asprey (CART)","mall_name":"Centrio","logo_url":null,"photo_url":null,"categories":[{"id":11,"name":"Jewelry & Watches"}]},{"contact":"-","description":"-","facebook":"-","hours":"-","id":5122,"location":"Ground Floor","mall_id":17,"map_id":null,"store_id":330,"twitter":"-","website":"-","x":0,"y":0,"store_name":"Chef Tony's Popcorn","mall_name":"Centrio","logo_url":null,"photo_url":null,"categories":[{"id":28,"name":"Food Stalls/Carts"}]},{"contact":"-","description":"-","facebook":"-","hours":"-","id":5123,"location":"Ground Floor","mall_id":17,"map_id":null,"store_id":2447,"twitter":"--","website":"-","x":0,"y":0,"store_name":"Chi Chi New York Rio","mall_name":"Centrio","logo_url":null,"photo_url":null,"categories":[{"id":18,"name":"Shoes, Bags, Leather Goods"}]},{"contact":"-","description":"-","facebook":"-","hours":"-","id":5124,"location":"Ground Floor","mall_id":17,"map_id":null,"store_id":2271,"twitter":"--","website":"-","x":0,"y":0,"store_name":"Colorstone","mall_name":"Centrio","logo_url":null,"photo_url":null,"categories":[{"id":28,"name":"Food Stalls/Carts"}]},{"contact":"-","description":"-","facebook":"-","hours":"-","id":5125,"location":"Third Floor","mall_id":17,"map_id":null,"store_id":2565,"twitter":"-","website":"-","x":0,"y":0,"store_name":"Dessert Strip Bistro","mall_name":"Centrio","logo_url":null,"photo_url":null,"categories":[{"id":28,"name":"Food Stalls/Carts"}]},{"contact":"-","description":"-","facebook":"-","hours":"-","id":5126,"location":"Ground Floor","mall_id":17,"map_id":null,"store_id":547,"twitter":"-","website":"-","x":0,"y":0,"store_name":"Filigrenasia","mall_name":"Centrio","logo_url":null,"photo_url":null,"categories":[{"id":19,"name":"Hobbies/Toys/Gifts & Novelties"}]},{"contact":"-","description":"-","facebook":"-","hours":"-","id":5127,"location":"Ground Floor","mall_id":17,"map_id":null,"store_id":2375,"twitter":"-","website":"-","x":0,"y":0,"store_name":"Fitflops","mall_name":"Centrio","logo_url":null,"photo_url":null,"categories":[{"id":18,"name":"Shoes, Bags, Leather Goods"}]},{"contact":"-","description":"-","facebook":"--","hours":"-","id":5128,"location":"Second Floor","mall_id":17,"map_id":null,"store_id":2273,"twitter":"-","website":"-","x":0,"y":0,"store_name":"Flywear","mall_name":"Centrio","logo_url":null,"photo_url":null,"categories":[{"id":28,"name":"Food Stalls/Carts"}]},{"contact":"-","description":"-","facebook":"-","hours":"-","id":5129,"location":"Third Floor","mall_id":17,"map_id":null,"store_id":2566,"twitter":"-","website":"-","x":0,"y":0,"store_name":"Gizmo","mall_name":"Centrio","logo_url":null,"photo_url":null,"categories":[{"id":28,"name":"Food Stalls/Carts"}]},{"contact":"-","description":"-","facebook":"-","hours":"-","id":5130,"location":"Second Floor","mall_id":17,"map_id":null,"store_id":2567,"twitter":"-","website":"-","x":0,"y":0,"store_name":"Gramp's Gourmet Popcorn","mall_name":"Centrio","logo_url":null,"photo_url":null,"categories":[{"id":28,"name":"Food Stalls/Carts"}]},{"contact":"-","description":"--","facebook":"-","hours":"-","id":5131,"location":"Ground Floor","mall_id":17,"map_id":null,"store_id":2568,"twitter":"-","website":"-","x":0,"y":0,"store_name":"House of Santa","mall_name":"Centrio","logo_url":null,"photo_url":null,"categories":[{"id":28,"name":"Food Stalls/Carts"}]},{"contact":"-","description":"-","facebook":"-","hours":"-","id":5132,"location":"Second Floor","mall_id":17,"map_id":null,"store_id":2569,"twitter":"-","website":"-","x":0,"y":0,"store_name":"JLG Natural Way","mall_name":"Centrio","logo_url":null,"photo_url":null,"categories":[{"id":28,"name":"Food Stalls/Carts"}]},{"contact":"-","description":"-","facebook":"-","hours":"-","id":5133,"location":"Second Floor","mall_id":17,"map_id":null,"store_id":2570,"twitter":"-","website":"-","x":0,"y":0,"store_name":"Juice & Co.","mall_name":"Centrio","logo_url":null,"photo_url":null,"categories":[{"id":28,"name":"Food Stalls/Carts"}]},{"contact":"-","description":"-","facebook":"-","hours":"-","id":5134,"location":"Ground Floor","mall_id":17,"map_id":null,"store_id":876,"twitter":"-","website":"-","x":0,"y":0,"store_name":"Keycards","mall_name":"Centrio","logo_url":null,"photo_url":null,"categories":[{"id":17,"name":"Services"}]},{"contact":"-","description":"-","facebook":"-","hours":"-","id":5135,"location":"Ground Floor","mall_id":17,"map_id":null,"store_id":889,"twitter":"-","website":"-","x":0,"y":0,"store_name":"King Corn","mall_name":"Centrio","logo_url":null,"photo_url":null,"categories":[{"id":27,"name":"Food Court"}]},{"contact":"-","description":"-","facebook":"-","hours":"-","id":5136,"location":"Second Floor","mall_id":17,"map_id":null,"store_id":2282,"twitter":"--","website":"-","x":0,"y":0,"store_name":"Lighter's Galore","mall_name":"Centrio","logo_url":null,"photo_url":null,"categories":[{"id":28,"name":"Food Stalls/Carts"}]},{"contact":"-","description":"-","facebook":"-","hours":"-","id":5137,"location":"Ground Floor","mall_id":17,"map_id":null,"store_id":2571,"twitter":"--","website":"-","x":0,"y":0,"store_name":"Missy Bonbon","mall_name":"Centrio","logo_url":null,"photo_url":null,"categories":[{"id":28,"name":"Food Stalls/Carts"}]},{"contact":"-","description":"-","facebook":"-","hours":"-","id":5138,"location":"Second Floor","mall_id":17,"map_id":null,"store_id":2572,"twitter":"--","website":"-","x":0,"y":0,"store_name":"Mr. Softy","mall_name":"Centrio","logo_url":null,"photo_url":null,"categories":[{"id":28,"name":"Food Stalls/Carts"}]},{"contact":"-","description":"-","facebook":"--","hours":"-","id":5139,"location":"Ground Floor","mall_id":17,"map_id":null,"store_id":2573,"twitter":"-","website":"-","x":0,"y":0,"store_name":"Puyo Handicrafts","mall_name":"Centrio","logo_url":null,"photo_url":null,"categories":[{"id":28,"name":"Food Stalls/Carts"}]},{"contact":"-","description":"-","facebook":"-","hours":"-","id":5140,"location":"Ground Floor","mall_id":17,"map_id":null,"store_id":2574,"twitter":"-","website":"-","x":0,"y":0,"store_name":"Slers","mall_name":"Centrio","logo_url":null,"photo_url":null,"categories":[{"id":28,"name":"Food Stalls/Carts"}]},{"contact":"-","description":"-","facebook":"-","hours":"-","id":5141,"location":"Ground Floor","mall_id":17,"map_id":null,"store_id":2575,"twitter":"--","website":"-","x":0,"y":0,"store_name":"Suelas","mall_name":"Centrio","logo_url":null,"photo_url":null,"categories":[{"id":28,"name":"Food Stalls/Carts"}]},{"contact":"-","description":"-","facebook":"-","hours":"-","id":5142,"location":"Second Floor, Third Floor","mall_id":17,"map_id":null,"store_id":1652,"twitter":"-","website":"-","x":0,"y":0,"store_name":"Thirsty","mall_name":"Centrio","logo_url":null,"photo_url":null,"categories":[{"id":27,"name":"Food Court"}]},{"contact":"-","description":"-","facebook":"-","hours":"-","id":5143,"location":"Second Floor","mall_id":17,"map_id":null,"store_id":2154,"twitter":"-","website":"-","x":0,"y":0,"store_name":"Vanity Box","mall_name":"Centrio","logo_url":null,"photo_url":null,"categories":[{"id":2,"name":"Apparel"}]},{"contact":"-","description":"-","facebook":"-","hours":"-","id":5144,"location":"Second Floor","mall_id":17,"map_id":null,"store_id":2576,"twitter":"-","website":"-","x":0,"y":0,"store_name":"Vjandep","mall_name":"Centrio","logo_url":null,"photo_url":null,"categories":[{"id":28,"name":"Food Stalls/Carts"}]},{"contact":"-","description":"-","facebook":"-","hours":"-","id":5145,"location":"Ground Floor","mall_id":17,"map_id":null,"store_id":1812,"twitter":"--","website":"-","x":0,"y":0,"store_name":"Zen Zest","mall_name":"Centrio","logo_url":null,"photo_url":null,"categories":[{"id":19,"name":"Hobbies/Toys/Gifts & Novelties"}]}]